llama_index/packs/fuzzy_citation/__init__.py
llama_index/packs/fuzzy_citation/base.py
llama_index_packs_fuzzy_citation-0.4.1.dist-info/METADATA
llama_index_packs_fuzzy_citation-0.4.1.dist-info/WHEEL
llama_index_packs_fuzzy_citation-0.4.1.dist-info/licenses/LICENSE
llama_index_packs_fuzzy_citation-0.4.1.dist-info/RECORD
