Metadata-Version: 2.4
Name: llama-index-packs-fuzzy-citation
Version: 0.4.1
Summary: llama-index packs fuzzy_citation integration
Author-email: Your Name <you@example.com>
Maintainer: logan-markewich
License-Expression: MIT
License-File: LICENSE
Keywords: citation,cite,engine,fuzzy,index,query
Requires-Python: <4.0,>=3.9
Requires-Dist: llama-index-core<0.15,>=0.13.0
Requires-Dist: thefuzz<0.23,>=0.22.1
